[
    {
        "app_id": "io.faceapp",
        "app_name": "FaceApp: Face Editor",
        "position": 1
    },
    {
        "app_id": "com.picsart.studio",
        "app_name": "Picsart Photo & Video Editor",
        "position": 2
    },
    {
        "app_id": "com.lightricks.pixaloop",
        "app_name": "Motionleap by Lightricks",
        "position": 3
    },
    {
        "app_id": "com.camerasideas.instashot",
        "app_name": "Video Editor & Maker - InShot",
        "position": 4
    },
    {
        "app_id": "photoeditor.layout.collagemaker",
        "app_name": "Collage Maker | Photo Editor",
        "position": 5
    },
    {
        "app_id": "photo.editor.photoeditor.photoeditorpro",
        "app_name": "Photo Editor Pro",
        "position": 6
    },
    {
        "app_id": "com.amazon.clouddrive.photos",
        "app_name": "Amazon Photos",
        "position": 7
    },
    {
        "app_id": "mobi.charmer.fotocollage",
        "app_name": "Pic Collage Maker Photo Editor",
        "position": 8
    },
    {
        "app_id": "com.bigwinepot.nwdn.international",
        "app_name": "Remini - AI Photo Enhancer",
        "position": 9
    },
    {
        "app_id": "vsin.t16_funny_photo",
        "app_name": "Photo Lab Picture Editor & Art",
        "position": 10
    },
    {
        "app_id": "com.adobe.lrmobile",
        "app_name": "Adobe Lightroom: Photo Editor",
        "position": 11
    },
    {
        "app_id": "com.vicman.toonmeapp",
        "app_name": "ToonMe - cartoons from photos",
        "position": 12
    },
    {
        "app_id": "com.lyrebirdstudio.toonart",
        "app_name": "ToonArt: Cartoon Yourself",
        "position": 13
    },
    {
        "app_id": "com.lyrebirdstudio.facelab",
        "app_name": "FaceLab: Face Editor, Aging",
        "position": 14
    },
    {
        "app_id": "com.niksoftware.snapseed",
        "app_name": "Snapseed",
        "position": 15
    },
    {
        "app_id": "com.lyrebirdstudio.face_camera",
        "app_name": "Face Live Camera: Photo Filters, Emojis, Stickers",
        "position": 16
    },
    {
        "app_id": "photo.editor.photoeditor.filtersforpictures",
        "app_name": "Photo Editor - Lumii",
        "position": 17
    },
    {
        "app_id": "com.adobe.psmobile",
        "app_name": "Photoshop Express Photo Editor",
        "position": 18
    },
    {
        "app_id": "com.magicv.airbrush",
        "app_name": "AirBrush: Easy Photo Editor",
        "position": 19
    },
    {
        "app_id": "com.cyberlink.photodirector",
        "app_name": "PhotoDirector - Photo Editor",
        "position": 20
    },
    {
        "app_id": "com.google.android.apps.photos",
        "app_name": "Google Photos",
        "position": 21
    },
    {
        "app_id": "photoeditor.cutout.backgrounderaser",
        "app_name": "Background Eraser - Remove BG",
        "position": 22
    },
    {
        "app_id": "com.handycloset.android.eraser",
        "app_name": "Background Eraser",
        "position": 23
    },
    {
        "app_id": "com.lightricks.facetune.free",
        "app_name": "Facetune2 Editor by Lightricks",
        "position": 24
    },
    {
        "app_id": "de.worldiety.photiety.cewe.mc.de",
        "app_name": "CEWE - Photo Books & More",
        "position": 25
    },
    {
        "app_id": "online.passportphoto.visa.id.app",
        "app_name": "Passport Photo AiD: US Passport Photo Booth App",
        "position": 26
    },
    {
        "app_id": "com.cam001.selfie",
        "app_name": "Sweet Selfie: Camera & Editor",
        "position": 27
    },
    {
        "app_id": "net.sourceforge.opencamera",
        "app_name": "Open Camera",
        "position": 28
    },
    {
        "app_id": "com.magic.retouch",
        "app_name": "Retouch Remove Objects Editor",
        "position": 29
    },
    {
        "app_id": "com.cyberlink.youcammakeup",
        "app_name": "YouCam Makeup - Selfie Editor",
        "position": 30
    },
    {
        "app_id": "com.prequel.app",
        "app_name": "PREQUEL Aesthetic Photo Editor",
        "position": 31
    },
    {
        "app_id": "de.dm.fotoparadies",
        "app_name": "Foto-Paradies",
        "position": 32
    },
    {
        "app_id": "de.rossmann.fotowelt",
        "app_name": "Rossmann Fotowelt",
        "position": 33
    },
    {
        "app_id": "com.lyrebirdstudio.cartoon",
        "app_name": "ToonApp: Cartoon Photo Editor",
        "position": 34
    },
    {
        "app_id": "photocollage.photoeditor.collagemaker",
        "app_name": "Collage Maker - Photo Collage",
        "position": 35
    },
    {
        "app_id": "com.cateater.stopmotionstudio",
        "app_name": "Stop Motion Studio",
        "position": 36
    },
    {
        "app_id": "com.pixum.android.photoworld",
        "app_name": "Pixum Photo Book & Prints",
        "position": 37
    },
    {
        "app_id": "com.google.android.apps.photos.scanner",
        "app_name": "PhotoScan by Google Photos",
        "position": 38
    },
    {
        "app_id": "com.video.fx.live",
        "app_name": "Snap FX: Effect Video Maker",
        "position": 39
    },
    {
        "app_id": "com.media.zatashima.studio",
        "app_name": "GIF Maker, GIF Editor",
        "position": 40
    },
    {
        "app_id": "com.vsco.cam",
        "app_name": "VSCO: Photo & Video Editor",
        "position": 41
    },
    {
        "app_id": "com.cardinalblue.piccollage.google",
        "app_name": "PicCollage: Photo Layout Edits",
        "position": 42
    },
    {
        "app_id": "hd.camera",
        "app_name": "HD Camera",
        "position": 43
    },
    {
        "app_id": "xprocamera.hd.camera",
        "app_name": "HD Camera for Android: XCamera",
        "position": 44
    },
    {
        "app_id": "com.lyrebirdstudio.collage_frame",
        "app_name": "DripArt Photo Editor: Pic Collage Maker, Stickers",
        "position": 45
    },
    {
        "app_id": "com.photoappworld.cut.paste.photo",
        "app_name": "Cut and Paste Photos",
        "position": 46
    },
    {
        "app_id": "com.photo.editor.photocollagemaker",
        "app_name": "Photo Collage Maker: Remove BG",
        "position": 47
    },
    {
        "app_id": "com.linecorp.b612.android",
        "app_name": "B612 Camera&Photo/Video Editor",
        "position": 48
    },
    {
        "app_id": "com.lyrebirdstudio.tbt",
        "app_name": "PicsApp Photo Editor & Collage",
        "position": 49
    },
    {
        "app_id": "jp.co.canon.ic.cameraconnect",
        "app_name": "Canon Camera Connect",
        "position": 50
    },
    {
        "app_id": "com.wemagineai.voila",
        "app_name": "Voila AI Artist Cartoon Photo",
        "position": 51
    },
    {
        "app_id": "com.dumplingsandwich.pencilsketch",
        "app_name": "Pencil Sketch",
        "position": 52
    },
    {
        "app_id": "com.bloomcreation.thesameapp",
        "app_name": "Bloom Creation",
        "position": 53
    },
    {
        "app_id": "com.ufotosoft.justshot",
        "app_name": "Sweet Snap: Beauty Face Camera",
        "position": 54
    },
    {
        "app_id": "com.km.recoverphotos",
        "app_name": "Recover Deleted Photos - Duplicate Photo Finder",
        "position": 55
    },
    {
        "app_id": "com.simplemobiletools.gallery",
        "app_name": "Simple Gallery - Photo Albums",
        "position": 56
    },
    {
        "app_id": "com.omdigitalsolutions.oishare",
        "app_name": "OM Image Share",
        "position": 57
    },
    {
        "app_id": "com.baiwang.piceditor",
        "app_name": "Photo Editor Pro, Filters & Effects - PicEditor",
        "position": 58
    },
    {
        "app_id": "com.photomyne",
        "app_name": "Photo Scan App by Photomyne",
        "position": 59
    },
    {
        "app_id": "com.ryzenrise.movepic",
        "app_name": "Movepic: Photo Motion Animator",
        "position": 60
    },
    {
        "app_id": "com.lyrebirdstudio.photo_background_changer",
        "app_name": "Photo Background Changer: Edit",
        "position": 61
    },
    {
        "app_id": "com.lyrebirdstudio.colorizer.lite",
        "app_name": "FaceArt Selfie Camera: Photo Filters and Effects",
        "position": 62
    },
    {
        "app_id": "intechsolutions.photoenhancer",
        "app_name": "AI Photo Enhancer/Unblur/Clear",
        "position": 63
    },
    {
        "app_id": "photo.editor.collage.maker.photoeditor",
        "app_name": "FotoApp Photo Editor: Camera Filters, Collage",
        "position": 64
    },
    {
        "app_id": "com.inshot.neonphotoeditor",
        "app_name": "Photo Editor & Photo Effects",
        "position": 65
    },
    {
        "app_id": "vn.remove.photo.content",
        "app_name": "Remove Unwanted Object",
        "position": 66
    },
    {
        "app_id": "photo.android.hd.camera",
        "app_name": "HD Camera for Android",
        "position": 67
    },
    {
        "app_id": "com.ror.removal",
        "app_name": "Photo Retouch- Object Removal",
        "position": 68
    },
    {
        "app_id": "com.feelty",
        "app_name": "Presets for Lightroom - FLTR",
        "position": 69
    },
    {
        "app_id": "com.photomyne.filmbox",
        "app_name": "FilmBox Film Negatives Scanner",
        "position": 70
    },
    {
        "app_id": "com.zmobileapps.passportphoto",
        "app_name": "Passport Size Photo Maker",
        "position": 71
    },
    {
        "app_id": "com.commsource.beautyplus",
        "app_name": "BeautyPlus-Snap Retouch Filter",
        "position": 72
    },
    {
        "app_id": "com.sony.playmemories.mobile",
        "app_name": "Imaging Edge Mobile",
        "position": 73
    },
    {
        "app_id": "com.energysh.onlinecamera1",
        "app_name": "Photo Editor BG Eraser MagiCut",
        "position": 74
    },
    {
        "app_id": "sweet.snapface.facefilter",
        "app_name": "Face Camera: Live Stickers",
        "position": 75
    },
    {
        "app_id": "com.kvadgroup.photostudio",
        "app_name": "Photo Studio",
        "position": 76
    },
    {
        "app_id": "com.journiapp.book",
        "app_name": "Journi Print: Photo Book",
        "position": 77
    },
    {
        "app_id": "com.hqgames.pencil.sketch.photo",
        "app_name": "Sketch Drawing Photo Editor",
        "position": 78
    },
    {
        "app_id": "com.kii.safe",
        "app_name": "Private Photo Vault - Keepsafe",
        "position": 79
    },
    {
        "app_id": "com.TTT.logomaker.logocreator.generator.designer",
        "app_name": "Logo Maker - Logo Creator",
        "position": 80
    },
    {
        "app_id": "com.meihillman.photocollage",
        "app_name": "Photo Collage Editor",
        "position": 81
    },
    {
        "app_id": "com.mt.mtxx.mtxx",
        "app_name": "Meitu-All in One Photo Editor",
        "position": 82
    },
    {
        "app_id": "com.camera12.iphone12",
        "app_name": "Camera iphone 12 - OS14 Camera",
        "position": 83
    },
    {
        "app_id": "com.etoolkit.lovecollage",
        "app_name": "Love Collage - Photo Editor",
        "position": 84
    },
    {
        "app_id": "com.photopro.photoeditorpro",
        "app_name": "Photo Editor - Photo Filters",
        "position": 85
    },
    {
        "app_id": "com.eabdrazakov.photomontage",
        "app_name": "Cut Paste Photo Seamless Edit",
        "position": 86
    },
    {
        "app_id": "gr.gamebrain.comica",
        "app_name": "comics and cartoon maker",
        "position": 87
    },
    {
        "app_id": "com.simplemobilephotoresizer",
        "app_name": "Photo & Picture Resizer",
        "position": 88
    },
    {
        "app_id": "com.vysionapps.face28",
        "app_name": "Face Changer Camera",
        "position": 89
    },
    {
        "app_id": "com.game.SuperMii",
        "app_name": "SuperMe - Cartoon Avatar Maker",
        "position": 90
    },
    {
        "app_id": "com.popsa.android",
        "app_name": "Popsa | Print Your Photos",
        "position": 91
    },
    {
        "app_id": "com.cerdillac.filmmaker",
        "app_name": "Film Maker Pro - Movie Maker",
        "position": 92
    },
    {
        "app_id": "com.photoeditor.photocollage.hdphotoeditor",
        "app_name": "HD Photo Editor - Pic Editor",
        "position": 93
    },
    {
        "app_id": "com.panasonic.avc.cng.imageapp",
        "app_name": "Panasonic Image App",
        "position": 94
    },
    {
        "app_id": "com.google.android.apps.photosgo",
        "app_name": "Gallery Go",
        "position": 95
    },
    {
        "app_id": "com.instagram.layout",
        "app_name": "Layout from Instagram: Collage",
        "position": 96
    },
    {
        "app_id": "com.lyrebirdstudio.neon_art",
        "app_name": "NeonArt Photo Editor & Effects",
        "position": 97
    },
    {
        "app_id": "com.kodakalaris.kodakmomentsapp",
        "app_name": "KODAK MOMENTS",
        "position": 98
    },
    {
        "app_id": "com.cyberlink.youperfect",
        "app_name": "YouCam Perfect - Photo Editor",
        "position": 99
    },
    {
        "app_id": "com.littlelf.smarthome",
        "app_name": "littlelf smart",
        "position": 100
    },
    {
        "app_id": "com.lyrebirdstudio.collage",
        "app_name": "Photo Collage Maker - Photo Editor & Photo Collage",
        "position": 101
    },
    {
        "app_id": "se.onceupon.onceuponapp",
        "app_name": "Once Upon | Photo Book Creator",
        "position": 102
    },
    {
        "app_id": "gallery.photomanager.picturegalleryapp.imagegallery",
        "app_name": "Gallery - photo gallery, album",
        "position": 103
    },
    {
        "app_id": "com.wtmp.svdsoftware",
        "app_name": "WTMP – Who touched my phone?",
        "position": 104
    },
    {
        "app_id": "jp.gr.java_conf.siranet.idphoto",
        "app_name": "ID Photo application",
        "position": 105
    },
    {
        "app_id": "de.posterxxl.posterxxl",
        "app_name": "posterXXL - Fotobuch erstellen",
        "position": 106
    },
    {
        "app_id": "com.photomyne.colorize",
        "app_name": "Colorize - Color to Old Photos",
        "position": 107
    },
    {
        "app_id": "com.picmax.cupace",
        "app_name": "Cupace - Cut and Paste Face Photo",
        "position": 108
    },
    {
        "app_id": "com.touchbyte.photosync",
        "app_name": "PhotoSync – Transfer Photos",
        "position": 109
    },
    {
        "app_id": "com.video.reface.app.faceplay.deepface.photo",
        "app_name": "FaceJoy Reface Play Face Swap",
        "position": 110
    },
    {
        "app_id": "com.fourchars.lmpfree",
        "app_name": "LockMyPix Secret Photo Vault: Hide Photos & Videos",
        "position": 111
    },
    {
        "app_id": "com.andromo.dev552033.app1073531",
        "app_name": "Guten Tag Bilder und Sprüche",
        "position": 112
    },
    {
        "app_id": "com.ryzenrise.storyart",
        "app_name": "StoryArt - Insta story maker",
        "position": 113
    },
    {
        "app_id": "com.gamebrain.cartoon",
        "app_name": "Cartoon Photo Editor",
        "position": 114
    },
    {
        "app_id": "com.newandromo.dev6813.app1241040",
        "app_name": "Sprüche und Zitate",
        "position": 115
    },
    {
        "app_id": "photo.photoeditor.snappycamera.prettymakeup",
        "app_name": "Pretty Makeup - Beauty Photo Editor Selfie Camera",
        "position": 116
    },
    {
        "app_id": "instagram.photo.video.downloader.repost.insta",
        "app_name": "Instore: Story Saver, Story, Video Downloader",
        "position": 117
    },
    {
        "app_id": "com.nand.addtext",
        "app_name": "Add Text: Text on Photo Editor",
        "position": 118
    },
    {
        "app_id": "com.baiwang.instabokeh",
        "app_name": "Photo Editor Pro: photo effects, background eraser",
        "position": 119
    },
    {
        "app_id": "com.jsdev.instasize",
        "app_name": "Instasize: Photo Editor + Picture Collage Maker",
        "position": 120
    },
    {
        "app_id": "com.lyrebirdstudio.montagenscolagem",
        "app_name": "Photo Editor Picsa: Collage",
        "position": 121
    },
    {
        "app_id": "com.baiwang.squareblend",
        "app_name": "Square Pic Collage - Sunset Photo Editor Pro",
        "position": 122
    },
    {
        "app_id": "com.photoroom.app",
        "app_name": "PhotoRoom Studio Photo Editor",
        "position": 123
    },
    {
        "app_id": "com.snaperfect.inframe1",
        "app_name": "InFrame - Photo Editor & Pics Frame",
        "position": 124
    },
    {
        "app_id": "com.mobile.bizo.tattoo.two",
        "app_name": "Tattoo my Photo 2.0",
        "position": 125
    },
    {
        "app_id": "com.pixlr.express",
        "app_name": "Pixlr – Free Photo Editor",
        "position": 126
    },
    {
        "app_id": "com.iudesk.android.photo.editor",
        "app_name": "Photo Editor",
        "position": 127
    },
    {
        "app_id": "io.instories",
        "app_name": "InStories: Insta Stories Maker",
        "position": 128
    },
    {
        "app_id": "photo.beauty.sticker.ar.camera",
        "app_name": "Beauty Camera - Selfie Camera",
        "position": 129
    },
    {
        "app_id": "com.loomatix.colorgrab",
        "app_name": "Color Grab (color detection)",
        "position": 130
    },
    {
        "app_id": "com.baiwang.styleinstaboxsnap",
        "app_name": "Photo Editor pro - SquarePic Stickers",
        "position": 131
    },
    {
        "app_id": "net.frameo.app",
        "app_name": "Frameo - Send photos to WiFi digital photo frames",
        "position": 132
    },
    {
        "app_id": "com.newandromo.dev6813.app1107900",
        "app_name": "Glückwünsche Geburtstagsgrüße",
        "position": 133
    },
    {
        "app_id": "com.youthhr.phonto",
        "app_name": "Phonto - Text on Photos",
        "position": 134
    },
    {
        "app_id": "net.braincake.bodytune",
        "app_name": "Bodytune: photo body editor",
        "position": 135
    },
    {
        "app_id": "photogrid.photocollagemaker.photoeditor.squarepic",
        "app_name": "Square Fit-Blur Photo Backgroud&Square Pic Editor",
        "position": 136
    },
    {
        "app_id": "com.everimaging.photoeffectstudio",
        "app_name": "Fotor Photo Editor - Design Maker & Photo Collage",
        "position": 137
    },
    {
        "app_id": "video.mojo",
        "app_name": "Mojo — Stories & Reels maker",
        "position": 138
    },
    {
        "app_id": "photo.selfie.beauty.hd.camera",
        "app_name": "HD Camera iphone Beauty Camera",
        "position": 139
    },
    {
        "app_id": "com.binghuo.photogrid.collagemaker",
        "app_name": "Collage Maker",
        "position": 140
    },
    {
        "app_id": "com.andromo.dev552033.app1037103",
        "app_name": "Guten Morgen Bilder Kostenlos für Whatsapp",
        "position": 141
    },
    {
        "app_id": "com.lyrebirdstudio.nocrop",
        "app_name": "Nocrop Photo Editor: Filters, Effects, Pic Collage",
        "position": 142
    },
    {
        "app_id": "jp.co.canon.bsd.easyphotoprinteditor",
        "app_name": "Easy-PhotoPrint Editor",
        "position": 143
    },
    {
        "app_id": "com.photoeditor.blendmephotoeditor",
        "app_name": "Blend Me Photo Editor",
        "position": 144
    },
    {
        "app_id": "com.memepick.mypic",
        "app_name": "Mypic-Make up Master",
        "position": 145
    },
    {
        "app_id": "com.newandromo.dev361940.app620968",
        "app_name": "Kostenlose Geburtstagsgrüße",
        "position": 146
    },
    {
        "app_id": "app.celebrate.celpho",
        "app_name": "celebrate: share photos & videos",
        "position": 147
    },
    {
        "app_id": "de.myposter.myposterapp",
        "app_name": "myposter - Photo Printing",
        "position": 148
    },
    {
        "app_id": "com.maginon.qc70se",
        "app_name": "Maginon Fly",
        "position": 149
    },
    {
        "app_id": "com.skysoft.removalfree",
        "app_name": "Object Removal Remove Objects",
        "position": 150
    },
    {
        "app_id": "com.photopro.collagemaker",
        "app_name": "Collage Maker - Photo Collage",
        "position": 151
    },
    {
        "app_id": "com.intermedia.hd.camera.professional",
        "app_name": "ProCam X - Lite ( HD Camera Pro )",
        "position": 152
    },
    {
        "app_id": "de.vsmedia.biometricpassportphoto",
        "app_name": "Passport Photo - ID Photo",
        "position": 153
    },
    {
        "app_id": "com.tickettothemoon.gradient.photo",
        "app_name": "Gradient: Face Beauty Editor",
        "position": 154
    },
    {
        "app_id": "com.binghuo.photogrid.collagemaker",
        "app_name": "Collage Maker",
        "position": 155
    },
    {
        "app_id": "com.photoscan.enhancer.remini.photomyne.colorize.scanner",
        "app_name": "PixeLeap Photo Enhancer & Scan",
        "position": 156
    },
    {
        "app_id": "com.aerotools.photo.sketch.maker.editor",
        "app_name": "Photo Sketch Maker",
        "position": 157
    },
    {
        "app_id": "vn.avengers.teamcoca.photoeditor.kawaii",
        "app_name": "Kawaii Photo Editor",
        "position": 158
    },
    {
        "app_id": "com.nikon.snapbridge.cmru",
        "app_name": "SnapBridge",
        "position": 159
    },
    {
        "app_id": "com.atomicadd.fotos",
        "app_name": "A+ Gallery - Photos & Videos",
        "position": 160
    },
    {
        "app_id": "hd.photo.video.selfie.camera",
        "app_name": "Beauty Camera:Selfie Camera HD",
        "position": 161
    },
    {
        "app_id": "com.accarunit.slowmotion",
        "app_name": "Time Cut : Smooth Slow Motion Video Editor﻿",
        "position": 162
    },
    {
        "app_id": "com.background.eraser.remover.photo.layers.editor",
        "app_name": "Cut Paste: Background Changer",
        "position": 163
    },
    {
        "app_id": "com.vyroai.AutoCutCut",
        "app_name": "Photo Background Change Editor",
        "position": 164
    },
    {
        "app_id": "com.emoji.android.emojidiy",
        "app_name": "Emoji Maker- Personal Animated Phone Emojis",
        "position": 165
    },
    {
        "app_id": "com.picphoto.photoshoteditor",
        "app_name": "PicPro: Photo Editor, Pic Layer",
        "position": 166
    },
    {
        "app_id": "com.compressphotopuma",
        "app_name": "Puma Image Compressor, Resizer",
        "position": 167
    },
    {
        "app_id": "com.short.hair.editor.for.girls",
        "app_name": "Short hair styler for women",
        "position": 168
    },
    {
        "app_id": "com.sertanta.slideshowmaker.movie.movieslideshowmaker",
        "app_name": "Make slideshow with music",
        "position": 169
    },
    {
        "app_id": "com.jeyluta.timestampcamerafree",
        "app_name": "Timestamp Camera",
        "position": 170
    },
    {
        "app_id": "com.Video_Mobile_VM.Damj_Sowar_2019",
        "app_name": "Photo Collage Editor",
        "position": 171
    },
    {
        "app_id": "de.vsmedia.imagesize",
        "app_name": "Image Size - Photo Resizer",
        "position": 172
    },
    {
        "app_id": "photo.hd.video.beauty.camera",
        "app_name": "Professional HD Camera with Selfie Camera",
        "position": 173
    },
    {
        "app_id": "com.irisstudio.photomixer",
        "app_name": "Ultimate Photo Blender / Mixer",
        "position": 174
    },
    {
        "app_id": "com.sweet.beauty.camera.plus.makeup.photo.editor",
        "app_name": "Beauty Sweet Plus - Beauty Camera - Sweet Face",
        "position": 175
    },
    {
        "app_id": "com.xenstudio.books.photo.frame.collage",
        "app_name": "Photobook Photo Editor App",
        "position": 176
    },
    {
        "app_id": "hippeis.com.photochecker",
        "app_name": "Photo Sherlock - Reverse Image Search",
        "position": 177
    },
    {
        "app_id": "com.camerafilter.ulook",
        "app_name": "Vintage Camera-Retro, Editor",
        "position": 178
    },
    {
        "app_id": "pics.phocus.autocrop.free",
        "app_name": "Automatic Background Changer",
        "position": 179
    },
    {
        "app_id": "com.makemeold.howwillilookwhenigetolder",
        "app_name": "How Will I Look When Old",
        "position": 180
    },
    {
        "app_id": "com.imaginstudio.imagetools.pixellab",
        "app_name": "PixelLab - Text on pictures",
        "position": 181
    },
    {
        "app_id": "com.baiwang.stylephotocollage",
        "app_name": "Collage Maker- Photo Collage , Photo Frame",
        "position": 182
    },
    {
        "app_id": "com.vyroai.bgeraser",
        "app_name": "Background Eraser- Photo Erase",
        "position": 183
    },
    {
        "app_id": "xyz.youworkshop.collagemaker",
        "app_name": "Collage Maker - Music Collage",
        "position": 184
    },
    {
        "app_id": "photo.beautycamera.selfie.prettycamera",
        "app_name": "Makeup Camera-Selfie Beauty Filter Photo Editor",
        "position": 185
    },
    {
        "app_id": "com.lyrebirdstudio.makeup.beauty.camera",
        "app_name": "Beauty Makeup Photo Editor: Makeover Beauty Camera",
        "position": 186
    },
    {
        "app_id": "com.journiapp.journi",
        "app_name": "Journi Blog - Travel Journal & Diary",
        "position": 187
    },
    {
        "app_id": "collage.maker.photoeditor",
        "app_name": "Collage Maker: Photo Editor",
        "position": 188
    },
    {
        "app_id": "jp.naver.linecamera.android",
        "app_name": "LINE Camera - Photo editor",
        "position": 189
    },
    {
        "app_id": "photoeditorfree.photoeditorpro.photoeditor",
        "app_name": "Photo Editor",
        "position": 190
    },
    {
        "app_id": "com.best.photo.app.womanhairstyles",
        "app_name": "Woman Hairstyles",
        "position": 191
    },
    {
        "app_id": "com.volio.stickers.heart.crown.camera.photoeditor",
        "app_name": "Photo Editor - Pic Editor",
        "position": 192
    },
    {
        "app_id": "com.snowcorp.epik",
        "app_name": "EPIK - Photo Editor",
        "position": 193
    },
    {
        "app_id": "com.eco.textonphoto.quotecreator",
        "app_name": "Text On Photo - Text to Photos",
        "position": 194
    },
    {
        "app_id": "com.coolapps.backgroundchanger",
        "app_name": "Simple Background Changer",
        "position": 195
    },
    {
        "app_id": "com.gif.gifmaker",
        "app_name": "GIF Maker - Video to GIF, GIF Editor",
        "position": 196
    },
    {
        "app_id": "com.gurushots.app",
        "app_name": "GuruShots - Photography",
        "position": 197
    },
    {
        "app_id": "hd.cam.proo",
        "app_name": "HDCam Pro",
        "position": 198
    }
]